{
  "Phương pháp kiểm tra_Update-0" : {
    "transaction" : "Phương pháp kiểm tra_Update-0",
    "sampleCount" : 5,
    "errorCount" : 0,
    "errorPct" : 0.0,
    "meanResTime" : 84.8,
    "medianResTime" : 79.0,
    "minResTime" : 47.0,
    "maxResTime" : 130.0,
    "pct1ResTime" : 130.0,
    "pct2ResTime" : 130.0,
    "pct3ResTime" : 130.0,
    "throughput" : 4.409171075837742,
    "receivedKBytesPerSec" : 4.7837783840388015,
    "sentKBytesPerSec" : 1.6680789792768962
  },
  "Phương pháp kiểm tra_Update-2" : {
    "transaction" : "Phương pháp kiểm tra_Update-2",
    "sampleCount" : 5,
    "errorCount" : 0,
    "errorPct" : 0.0,
    "meanResTime" : 68.2,
    "medianResTime" : 79.0,
    "minResTime" : 39.0,
    "maxResTime" : 99.0,
    "pct1ResTime" : 99.0,
    "pct2ResTime" : 99.0,
    "pct3ResTime" : 99.0,
    "throughput" : 4.672897196261682,
    "receivedKBytesPerSec" : 22.552205023364486,
    "sentKBytesPerSec" : 1.0313230140186915
  },
  "Phương pháp kiểm tra_Update-1" : {
    "transaction" : "Phương pháp kiểm tra_Update-1",
    "sampleCount" : 5,
    "errorCount" : 0,
    "errorPct" : 0.0,
    "meanResTime" : 82.0,
    "medianResTime" : 83.0,
    "minResTime" : 56.0,
    "maxResTime" : 108.0,
    "pct1ResTime" : 108.0,
    "pct2ResTime" : 108.0,
    "pct3ResTime" : 108.0,
    "throughput" : 4.488330341113106,
    "receivedKBytesPerSec" : 4.216575964991023,
    "sentKBytesPerSec" : 1.525331014362657
  },
  "Phương pháp kiểm tra_Delete-1" : {
    "transaction" : "Phương pháp kiểm tra_Delete-1",
    "sampleCount" : 5,
    "errorCount" : 0,
    "errorPct" : 0.0,
    "meanResTime" : 84.4,
    "medianResTime" : 73.0,
    "minResTime" : 56.0,
    "maxResTime" : 126.0,
    "pct1ResTime" : 126.0,
    "pct2ResTime" : 126.0,
    "pct3ResTime" : 126.0,
    "throughput" : 5.015045135406218,
    "receivedKBytesPerSec" : 4.934726053159478,
    "sentKBytesPerSec" : 1.9080679538615848
  },
  "Phương pháp kiểm tra_View-0" : {
    "transaction" : "Phương pháp kiểm tra_View-0",
    "sampleCount" : 5,
    "errorCount" : 0,
    "errorPct" : 0.0,
    "meanResTime" : 301.4,
    "medianResTime" : 295.0,
    "minResTime" : 175.0,
    "maxResTime" : 433.0,
    "pct1ResTime" : 433.0,
    "pct2ResTime" : 433.0,
    "pct3ResTime" : 433.0,
    "throughput" : 4.0551500405515,
    "receivedKBytesPerSec" : 4.3996793896999185,
    "sentKBytesPerSec" : 0.8672635340632603
  },
  "Phương pháp kiểm tra_Delete-2" : {
    "transaction" : "Phương pháp kiểm tra_Delete-2",
    "sampleCount" : 5,
    "errorCount" : 0,
    "errorPct" : 0.0,
    "meanResTime" : 87.6,
    "medianResTime" : 58.0,
    "minResTime" : 41.0,
    "maxResTime" : 162.0,
    "pct1ResTime" : 162.0,
    "pct2ResTime" : 162.0,
    "pct3ResTime" : 162.0,
    "throughput" : 5.376344086021506,
    "receivedKBytesPerSec" : 25.947160618279568,
    "sentKBytesPerSec" : 1.3062836021505375
  },
  "Phương pháp kiểm tra_View" : {
    "transaction" : "Phương pháp kiểm tra_View",
    "sampleCount" : 5,
    "errorCount" : 0,
    "errorPct" : 0.0,
    "meanResTime" : 475.8,
    "medianResTime" : 459.0,
    "minResTime" : 316.0,
    "maxResTime" : 675.0,
    "pct1ResTime" : 675.0,
    "pct2ResTime" : 675.0,
    "pct3ResTime" : 675.0,
    "throughput" : 3.389830508474576,
    "receivedKBytesPerSec" : 23.222325211864405,
    "sentKBytesPerSec" : 2.625132415254237
  },
  "Phương pháp kiểm tra_View-1" : {
    "transaction" : "Phương pháp kiểm tra_View-1",
    "sampleCount" : 5,
    "errorCount" : 0,
    "errorPct" : 0.0,
    "meanResTime" : 93.6,
    "medianResTime" : 85.0,
    "minResTime" : 58.0,
    "maxResTime" : 140.0,
    "pct1ResTime" : 140.0,
    "pct2ResTime" : 140.0,
    "pct3ResTime" : 140.0,
    "throughput" : 4.528985507246377,
    "receivedKBytesPerSec" : 4.254769587862318,
    "sentKBytesPerSec" : 1.5391474184782608
  },
  "Phương pháp kiểm tra_View-2" : {
    "transaction" : "Phương pháp kiểm tra_View-2",
    "sampleCount" : 5,
    "errorCount" : 0,
    "errorPct" : 0.0,
    "meanResTime" : 80.6,
    "medianResTime" : 86.0,
    "minResTime" : 51.0,
    "maxResTime" : 109.0,
    "pct1ResTime" : 109.0,
    "pct2ResTime" : 109.0,
    "pct3ResTime" : 109.0,
    "throughput" : 4.355400696864112,
    "receivedKBytesPerSec" : 21.01991234756098,
    "sentKBytesPerSec" : 0.9612505444250872
  },
  "Phương pháp kiểm tra_Delete-0" : {
    "transaction" : "Phương pháp kiểm tra_Delete-0",
    "sampleCount" : 5,
    "errorCount" : 0,
    "errorPct" : 0.0,
    "meanResTime" : 75.2,
    "medianResTime" : 55.0,
    "minResTime" : 48.0,
    "maxResTime" : 117.0,
    "pct1ResTime" : 117.0,
    "pct2ResTime" : 117.0,
    "pct3ResTime" : 117.0,
    "throughput" : 4.798464491362764,
    "receivedKBytesPerSec" : 5.614765774952015,
    "sentKBytesPerSec" : 1.6054237643953935
  },
  "Phương pháp kiểm tra_Add" : {
    "transaction" : "Phương pháp kiểm tra_Add",
    "sampleCount" : 5,
    "errorCount" : 0,
    "errorPct" : 0.0,
    "meanResTime" : 273.8,
    "medianResTime" : 218.0,
    "minResTime" : 207.0,
    "maxResTime" : 367.0,
    "pct1ResTime" : 367.0,
    "pct2ResTime" : 367.0,
    "pct3ResTime" : 367.0,
    "throughput" : 3.834355828220859,
    "receivedKBytesPerSec" : 26.26758411618098,
    "sentKBytesPerSec" : 3.592461896088957
  },
  "Phương pháp kiểm tra_Add-2" : {
    "transaction" : "Phương pháp kiểm tra_Add-2",
    "sampleCount" : 5,
    "errorCount" : 0,
    "errorPct" : 0.0,
    "meanResTime" : 84.6,
    "medianResTime" : 83.0,
    "minResTime" : 37.0,
    "maxResTime" : 129.0,
    "pct1ResTime" : 129.0,
    "pct2ResTime" : 129.0,
    "pct3ResTime" : 129.0,
    "throughput" : 4.370629370629371,
    "receivedKBytesPerSec" : 21.09340854458042,
    "sentKBytesPerSec" : 0.9646115603146854
  },
  "Phương pháp kiểm tra_Add-1" : {
    "transaction" : "Phương pháp kiểm tra_Add-1",
    "sampleCount" : 5,
    "errorCount" : 0,
    "errorPct" : 0.0,
    "meanResTime" : 96.8,
    "medianResTime" : 82.0,
    "minResTime" : 69.0,
    "maxResTime" : 142.0,
    "pct1ResTime" : 142.0,
    "pct2ResTime" : 142.0,
    "pct3ResTime" : 142.0,
    "throughput" : 4.248088360237893,
    "receivedKBytesPerSec" : 3.9908798853016143,
    "sentKBytesPerSec" : 1.4436862786745963
  },
  "Phương pháp kiểm tra_Update" : {
    "transaction" : "Phương pháp kiểm tra_Update",
    "sampleCount" : 5,
    "errorCount" : 0,
    "errorPct" : 0.0,
    "meanResTime" : 235.2,
    "medianResTime" : 240.0,
    "minResTime" : 142.0,
    "maxResTime" : 308.0,
    "pct1ResTime" : 308.0,
    "pct2ResTime" : 308.0,
    "pct3ResTime" : 308.0,
    "throughput" : 4.068348250610253,
    "receivedKBytesPerSec" : 27.87056931448332,
    "sentKBytesPerSec" : 3.8196386798209923
  },
  "Phương pháp kiểm tra_Delete" : {
    "transaction" : "Phương pháp kiểm tra_Delete",
    "sampleCount" : 5,
    "errorCount" : 0,
    "errorPct" : 0.0,
    "meanResTime" : 247.6,
    "medianResTime" : 174.0,
    "minResTime" : 152.0,
    "maxResTime" : 405.0,
    "pct1ResTime" : 405.0,
    "pct2ResTime" : 405.0,
    "pct3ResTime" : 405.0,
    "throughput" : 4.378283712784588,
    "receivedKBytesPerSec" : 30.561617502189144,
    "sentKBytesPerSec" : 4.194430002189142
  },
  "Phương pháp kiểm tra_Add-0" : {
    "transaction" : "Phương pháp kiểm tra_Add-0",
    "sampleCount" : 5,
    "errorCount" : 0,
    "errorPct" : 0.0,
    "meanResTime" : 92.0,
    "medianResTime" : 99.0,
    "minResTime" : 52.0,
    "maxResTime" : 110.0,
    "pct1ResTime" : 110.0,
    "pct2ResTime" : 110.0,
    "pct3ResTime" : 110.0,
    "throughput" : 4.180602006688963,
    "receivedKBytesPerSec" : 4.535789872491639,
    "sentKBytesPerSec" : 1.5734414193143813
  },
  "Total" : {
    "transaction" : "Total",
    "sampleCount" : 80,
    "errorCount" : 0,
    "errorPct" : 0.0,
    "meanResTime" : 153.97500000000008,
    "medianResTime" : 107.5,
    "minResTime" : 37.0,
    "maxResTime" : 675.0,
    "pct1ResTime" : 357.5000000000001,
    "pct2ResTime" : 431.6000000000001,
    "pct3ResTime" : 675.0,
    "throughput" : 40.4244567963618,
    "receivedKBytesPerSec" : 139.12092597271348,
    "sentKBytesPerSec" : 18.232456417382515
  }
}